operacionestest/__init__.py
operacionestest/modulo.py
operacionestestjeronimo-0.1.1.dist-info/METADATA
operacionestestjeronimo-0.1.1.dist-info/WHEEL
operacionestestjeronimo-0.1.1.dist-info/top_level.txt
operacionestestjeronimo-0.1.1.dist-info/RECORD
