Metadata-Version: 2.4
Name: operacionestestjeronimo
Version: 0.1.1
Summary: libreria de operaciones básicas
Author: Jerónimo Loaiza
License: MIT
Requires-Python: >=3.11.13
Dynamic: author
Dynamic: description
Dynamic: description-content-type
Dynamic: license
Dynamic: requires-python
Dynamic: summary
